aEye/__init__.py
aEye/auxiliary.py
aEye/extractor.py
aEye/labeler.py
aEye/video.py
aEye-1.2.4.dist-info/LICENSE
aEye-1.2.4.dist-info/METADATA
aEye-1.2.4.dist-info/WHEEL
aEye-1.2.4.dist-info/top_level.txt
aEye-1.2.4.dist-info/RECORD
