Metadata-Version: 2.1
Name: aEye
Version: 1.2.4
Summary: Extensible Video Processing Framework
Home-page: https://github.com/DISHDevEx/aEye
Author-email: devex@dish.com
License: Dish Wireless
License-File: LICENSE
Requires-Dist: boto3
Requires-Dist: opencv-python
Requires-Dist: static-ffmpeg
